<GlossaryTerm id="CDR0000045333"><TermName>cancer</TermName><TermPronunciation>(KAN-ser)</TermPronunciation><TermDefinition><DefinitionText>A term for
          diseases in which abnormal cells divide without control and
          can invade nearby tissues. Cancer cells
          can also spread to other parts of the body through the
          blood and lymph systems. There are several main types of
          cancer. Carcinoma is a
          cancer that begins in the skin or
          in tissues that line or cover internal organs. Sarcoma is a
          cancer that begins in bone,
          cartilage, fat, muscle, blood vessels, or other connective
          or supportive tissue. Leukemia is a
          cancer that begins in blood-forming
          tissue, such as the bone marrow, and causes too many
          abnormal blood cells to be made. Lymphoma and multiple
          myeloma are cancers that begin in the
          cells of the immune system. Central nervous system cancers
          are cancers that begin in the tissues of
          the brain and spinal cord. Also called malignancy.</DefinitionText><Dictionary>Cancer.gov</Dictionary><Audience>Patient</Audience></TermDefinition><MediaLink ref="CDR0000705333" type="audio/mpeg" alt="Pronunciation of dictionary term &quot;cancer&quot;" language="en" id="_3"/><MediaLink ref="CDR0000705332" type="audio/mpeg" alt="Pronunciation of dictionary term &quot;cáncer&quot;" language="es" id="_4"/><SpanishTermName>cáncer</SpanishTermName><SpanishTermDefinition><DefinitionText>Término que describe las
enfermedades en las que hay células anormales que se
multiplican sin control e invaden los tejidos cercanos. Es
posible que las células cancerosas también
se diseminen a otras partes del cuerpo a través de los
sistemas sanguíneo y linfático. Hay varios tipos de
cánceres. El carcinoma
es un cáncer que empieza en la
piel o en los tejidos que revisten o cubren los órganos
internos. El sarcoma empieza en el hueso, el cartílago, la
grasa, el músculo, los vasos sanguíneos u otro tejido
conjuntivo o de sostén. La leucemia afecta los tejidos
donde se forman las células sanguíneas, como la médula
ósea, y hace que se produzcan muchas células sanguíneas
anormales. El linfoma y el mieloma múltiple afectan las
células del sistema inmunitario. Los cánceres
del sistema nervioso central empiezan en los tejidos del
encéfalo y la médula espinal. También se llama neoplasia maligna.</DefinitionText><Dictionary>Cancer.gov</Dictionary><Audience>Patient</Audience></SpanishTermDefinition><DateLastModified>2020-06-10</DateLastModified><RelatedInformation><RelatedExternalRef UseWith="en" xref="https://www.cancer.gov/about-cancer/understanding/what-is-cancer">What
Is Cancer? </RelatedExternalRef><RelatedExternalRef UseWith="es" xref="https://www.cancer.gov/espanol/cancer/naturaleza/que-es/">¿Qué
es el cáncer?</RelatedExternalRef></RelatedInformation></GlossaryTerm>
