<GlossaryTerm id="CDR0000045687"><TermName>fallopian tube</TermName><TermPronunciation>(fuh-LOH-pee-in...)</TermPronunciation><TermDefinition><DefinitionText>One of two long, slender tubes that connect the ovaries to the uterus. Eggs pass from the ovaries, through the fallopian tubes, to the uterus. In the female reproductive tract, there is one ovary and one fallopian tube on each side of the uterus.</DefinitionText><Dictionary>Cancer.gov</Dictionary><Audience>Patient</Audience></TermDefinition><MediaLink ref="CDR0000707084" type="audio/mpeg" alt="Pronunciation of dictionary term &quot;fallopian tube&quot;" language="en" id="_3"/><MediaLink ref="CDR0000707083" type="audio/mpeg" alt="Pronunciation of dictionary term &quot;trompa de Falopio&quot;" language="es" id="_4"/><MediaLink ref="CDR0000609921" type="image/jpeg" alt="Anatomy of the female reproductive system; drawing shows the uterus, myometrium (muscular outer layer of the uterus), endometrium (inner lining of the uterus), ovaries, fallopian tubes, cervix, and vagina." language="en" audience="Patients" placement="image-center" id="_3"><Caption language="en">Anatomy of the female reproductive system. The organs in the female reproductive system include the uterus, ovaries, fallopian tubes, cervix, and vagina. The uterus has a muscular outer layer called the myometrium and an inner lining called the endometrium. </Caption></MediaLink><MediaLink ref="CDR0000650412" type="image/jpeg" alt="Anatomía del aparato reproductor femenino. En el dibujo de una mujer adulta se señalan el útero, el miometrio, que es la capa muscular externa del útero; el endometrio, que es la capa de tejido interno que reviste el útero; los ovarios, las trompas de Falopio, el cuello uterino y la vagina." language="es" audience="Patients" placement="image-center" id="_4"><Caption language="es">Anatomía del aparato reproductor femenino. Los órganos del aparato reproductor femenino incluyen el útero, los ovarios, las trompas de Falopio, el cuello uterino y la vagina. El útero tiene una capa muscular externa llamada miometrio y una capa de tejido interno llamada endometrio.</Caption></MediaLink><SpanishTermName>trompa de Falopio</SpanishTermName><SpanishTermDefinition><DefinitionText>Cada uno de los dos tubos largos y delgados que conectan los ovarios con el útero. Los óvulos pasan desde los ovarios hasta el útero por las trompas de Falopio. En  el aparato reproductor de la mujer, hay un ovario y una trompa de Falopio a cada lado del útero. También se llama trompa uterina.</DefinitionText><Dictionary>Cancer.gov</Dictionary><Audience>Patient</Audience></SpanishTermDefinition><DateLastModified>2020-06-10</DateLastModified></GlossaryTerm>
