<GlossaryTerm id="CDR0000046779"><TermName>stage V Wilms tumor</TermName><TermPronunciation>(… wilmz TOO-mer)</TermPronunciation><TermDefinition><DefinitionText>Cancer cells are found in both kidneys when the cancer is first diagnosed. The cancer in each kidney is staged separately as stage I, II, III, or IV.</DefinitionText><Dictionary>Cancer.gov</Dictionary><Audience>Patient</Audience></TermDefinition><MediaLink ref="CDR0000731791" type="audio/mpeg" alt="Pronunciation of dictionary term &quot;stage V Wilms tumor&quot;" language="en" id="_3"/><MediaLink ref="CDR0000731790" type="audio/mpeg" alt="Pronunciation of dictionary term &quot;tumor de Wilms en estadio V&quot;" language="es" id="_4"/><SpanishTermName>tumor de Wilms en estadio V</SpanishTermName><SpanishTermDefinition><DefinitionText>Cuando se diagnostica el cáncer por primera vez, se encuentran células cancerosas en ambos riñones. El cáncer en cada riñón se estadifica por separado en estadio I, II, III o IV.</DefinitionText><Dictionary>Cancer.gov</Dictionary><Audience>Patient</Audience></SpanishTermDefinition><DateLastModified>2021-06-15</DateLastModified><RelatedInformation><RelatedSummaryRef UseWith="en" href="CDR0000415235" url="/types/kidney/patient/wilms-treatment-pdq">Wilms Tumor</RelatedSummaryRef><RelatedSummaryRef UseWith="es" href="CDR0000483772" url="/espanol/tipos/rinon/paciente/tratamiento-wilms-pdq">Tratamiento del tumor de Wilms y otros tumores renales infantiles</RelatedSummaryRef></RelatedInformation></GlossaryTerm>
