<GlossaryTerm id="CDR0000793190"><TermName>pevonedistat</TermName><TermPronunciation>(PEH-voh-NEH-dih-stat)</TermPronunciation><TermDefinition><DefinitionText>A substance being studied in the treatment of some types of cancer. Pevonedistat blocks an enzyme called NEDD8-activating enzyme (NAE), which is involved in cell division. Blocking this enzyme may help keep cancer cells from growing and may kill them. Pevonedistat is a type of NAE inhibitor and a type of targeted therapy.</DefinitionText><Dictionary>Cancer.gov</Dictionary><Audience>Patient</Audience></TermDefinition><MediaLink ref="CDR0000795235" type="audio/mpeg" alt="Pronunciation of dictionary term &quot;pevonedistat&quot;" language="en" id="_3"/><MediaLink ref="CDR0000795234" type="audio/mpeg" alt="Pronunciation of dictionary term &quot;pevonedistat&quot;" language="es" id="_4"/><SpanishTermName>pevonedistat</SpanishTermName><SpanishTermDefinition><DefinitionText>Sustancia en estudio para el tratamiento de algunos tipos de cáncer. El pevonedistat bloquea la enzima activadora de NEDD8 (NAE), que participa en la división celular. Es posible que bloquear esta enzima ayude a evitar la formación células cancerosas y las destruya. El  pevonedistat es un tipo de inhibidor de la NAE y se usa para un tipo de terapia dirigida.</DefinitionText><Dictionary>Cancer.gov</Dictionary><Audience>Patient</Audience></SpanishTermDefinition><DateFirstPublished>2018-06-26</DateFirstPublished></GlossaryTerm>
