<GlossaryTerm id="CDR0000802353"><TermName>cold tumor</TermName><TermPronunciation>(kold TOO-mer)</TermPronunciation><TermDefinition><DefinitionText>Describes a tumor that is not likely to trigger a strong immune response. Cold tumors tend to be surrounded by cells that are able to suppress the immune response and keep T cells (a type of immune cell) from attacking the tumor cells and killing them. Cold tumors usually do not respond to immunotherapy. Most cancers of the breast, ovary, prostate, pancreas, and brain (glioblastoma) are considered cold tumors.</DefinitionText><Dictionary>Cancer.gov</Dictionary><Audience>Patient</Audience></TermDefinition><MediaLink ref="CDR0000804456" type="audio/mpeg" alt="Pronunciation of dictionary term &quot;cold tumor&quot;" language="en" id="_3"/><MediaLink ref="CDR0000804457" type="audio/mpeg" alt="Pronunciation of dictionary term &quot;tumor frío&quot;" language="es" id="_4"/><SpanishTermName>tumor frío</SpanishTermName><SpanishTermDefinition><DefinitionText>Descripción de un tumor que es probable que no desencadene una respuesta inmunitaria fuerte. Los tumores fríos tienden a estar rodeados de células capaces de inhibir la respuesta inmunitaria e impedir que las células T (tipo de célula inmunitaria) ataquen las células tumorales y las destruyan. Por lo general, los tumores fríos no responden a la inmunoterapia. La mayoría de los cánceres de mama, ovario, próstata, páncreas y encéfalo (glioblastoma) se consideran tumores fríos.</DefinitionText><Dictionary>Cancer.gov</Dictionary><Audience>Patient</Audience></SpanishTermDefinition><DateFirstPublished>2020-11-18</DateFirstPublished></GlossaryTerm>
