<?xml version="1.0" ?>
<GlossaryTerm id="CDR0000808378">
  <TermName>stage I leiomyosarcoma of the uterus</TermName>
  <TermPronunciation>(... LY-oh-MY-oh-sar-KOH-muh ... YOO-ter-us)</TermPronunciation>
  <TermDefinition>
    <DefinitionText>In stage I, the tumor is found in the uterus only. Stage I is divided into stages IA and IB. In stage IA, the tumor is 5 centimeters or smaller. In stage IB, the tumor is larger than 5 centimeters.</DefinitionText>
    <Dictionary>Cancer.gov</Dictionary>
    <Audience>Patient</Audience>
  </TermDefinition>
  <MediaLink ref="CDR0000809796" type="audio/mpeg" alt="Pronunciation of dictionary term &quot;stage I leiomyosarcoma of the uterus&quot;" language="en" id="_4"/>
  <MediaLink ref="CDR0000809797" type="audio/mpeg" alt="Pronunciation of dictionary term &quot;leiomiosarcoma uterino en estadio I&quot;" language="es" id="_5"/>
  <SpanishTermName>leiomiosarcoma uterino en estadio I</SpanishTermName>
  <SpanishTermDefinition>
    <DefinitionText>En el estadio I, el tumor se encuentra solo en el útero. El estadio I se divide en los estadios IA y IB. En el estadio IA, el tumor mide 5 cm o menos. En el estadio IB, el tumor mide más de 5 cm. También se llama leiomiosarcoma de útero en estadio I.</DefinitionText>
    <Dictionary>Cancer.gov</Dictionary>
    <Audience>Patient</Audience>
  </SpanishTermDefinition>
  <DateFirstPublished>2022-02-10</DateFirstPublished>
  <RelatedInformation>
    <RelatedSummaryRef UseWith="en" href="CDR0000257805" url="/types/uterine/patient/uterine-sarcoma-treatment-pdq">Uterine Sarcoma Treatment</RelatedSummaryRef>
    <RelatedSummaryRef UseWith="es" href="CDR0000452962" url="/espanol/tipos/uterino/paciente/tratamiento-sarcoma-uterino-pdq">Tratamiento del sarcoma uterino</RelatedSummaryRef>
  </RelatedInformation>
</GlossaryTerm>
